tri_table/__init__.py
tri_table/db_compat.py
tri_table/templates/tri_table/header.html
tri_table/templates/tri_table/list.html
tri_table/templates/tri_table/paginator.html
tri_table/templates/tri_table/table.html
tri_table/templates/tri_table/table_container.html
tri_table/templates/tri_table/table_header_rows.html
tri.table-8.1.1.dist-info/AUTHORS.rst
tri.table-8.1.1.dist-info/LICENSE
tri.table-8.1.1.dist-info/METADATA
tri.table-8.1.1.dist-info/WHEEL
tri.table-8.1.1.dist-info/top_level.txt
tri.table-8.1.1.dist-info/RECORD
