Metadata-Version: 2.1
Name: tri.table
Version: 8.1.1
Summary: tri.table is a library to make full featured HTML tables easily
Home-page: https://github.com/TriOptima/tri.table
Author: Anders Hovmöller
Author-email: anders.hovmoller@trioptima.com
License: BSD
Keywords: tri.table
Platform: UNKNOWN
Classifier: Development Status :: 5 - Production/Stable
Classifier: Intended Audience :: Developers
Classifier: License :: OSI Approved :: BSD License
Classifier: Natural Language :: English
Classifier: Programming Language :: Python :: 3
Classifier: Programming Language :: Python :: 3.6
Requires-Dist: Django (>=2.0)
Requires-Dist: tri.declarative (<5.0.0,>=4.0.0)
Requires-Dist: tri.struct (<4.0.0,>=3.0.0)
Requires-Dist: tri.named-struct (<2.0.0,>=1.0.0)
Requires-Dist: tri.form (<8.0.0,>=7.2.4)
Requires-Dist: tri.query (<7.0.0,>=6.1.0)
